[ [
	{
		"id":1,
		"nombre":"Aguascalientes",
		"cod":"AGS"
	},{
		"id":2,
		"nombre":"Baja California",
		"cod":"BCN"
	},{
		"id":3,
		"nombre":"Baja California Sur",
		"cod":"BCS"
	},{
		"id":4,
		"nombre":"Campeche",
		"cod":"CAM"
	},{
		"id":5,
		"nombre":"Coahuila",
		"cod":"COA"
	},{
		"id":6,
		"nombre":"Colima",
		"cod":"COL"
	},{
		"id":7,
		"nombre":"Chiapas",
		"cod":"CHP"
	},{
		"id":8,
		"nombre":"Chihuahua",
		"cod":"CHI"
	},{
		"id":9,
		"nombre":"Ciudad de México",
		"cod":"CDMX"
	},{
		"id":10,
		"nombre":"Durango",
		"cod":"DUR"
	},{
		"id":11,
		"nombre":"Guanajuato",
		"cod":"GTO"
	},{
		"id":12,
		"nombre":"Guerrero",
		"cod":"GRO"
	},{
		"id":13,
		"nombre":"Hidalgo",
		"cod":"HGO"
	},{
		"id":14,
		"nombre":"Jalisco",
		"cod":"JAL"
	},{
		"id":15,
		"nombre":"Estado de México",
		"cod":"EDO_MEX"
	},{
		"id":16,
		"nombre":"Michoacán",
		"cod":"MIC"
	},{
		"id":17,
		"nombre":"Morelos",
		"cod":"MOR"
	},{
		"id":18,
		"nombre":"Nayarit",
		"cod":"NAY"
	},{
		"id":19,
		"nombre":"Nuevo León",
		"cod":"NLE"
	},{
		"id":20,
		"nombre":"Oaxaca",
		"cod":"OAX"
	},{
		"id":21,
		"nombre":"Puebla",
		"cod":"PUE"
	},{
		"id":22,
		"nombre":"Querétaro",
		"cod":"QRO"
	},{
		"id":23,
		"nombre":"Quintana Roo",
		"cod":"ROO"
	},{
		"id":24,
		"nombre":"San Luis Potosí",
		"cod":"SLP"
	},{
		"id":25,
		"nombre":"Sinaloa",
		"cod":"SIN"
	},{
		"id":26,
		"nombre":"Sonora",
		"cod":"SON"
	},{
		"id":27,
		"nombre":"Tabasco",
		"cod":"TAB"
	},{
		"id":28,
		"nombre":"Tamaulipas",
		"cod":"TAM"
	},{
		"id":29,
		"nombre":"Tlaxcala",
		"cod":"TLX"
	},{
		"id":30,
		"nombre":"Veracruz",
		"cod":"VER"
	},{
		"id":31,
		"nombre":"Yucatán",
		"cod":"YUC"
	},{
		"id":32,
		"nombre":"Zacatecas",
		"cod":"ZAC"
	},{
		"id":33,
		"nombre":"Federación",
		"cod":"FED"
	}
]]